metrics_py/__init__.py
metrics_py/metrics.py
metrics_py/config/__init__.py
metrics_py/config/metric_config.py
metrics_py/config/option.py
metrics_py/metrics_manager/__init__.py
metrics_py/metrics_manager/metric_info.py
metrics_py/metrics_manager/metrics.py
metrics_py/middleware/__init__.py
metrics_py/middleware/base.py
metrics_py/middleware/fastapi.py
metrics_py/middleware/flask.py
metrics_py/middleware/rpc.py
metrics_py/reporter/__init__.py
metrics_py/reporter/abstract.py
metrics_py/reporter/collecotr_reporter.py
metrics_py/reporter/push_gateway_reporter.py
metrics_py/util/__init__.py
metrics_py/util/env.py
metrics_py/util/metric.py
everfir_metrics-0.2.5.dist-info/METADATA
everfir_metrics-0.2.5.dist-info/WHEEL
everfir_metrics-0.2.5.dist-info/top_level.txt
everfir_metrics-0.2.5.dist-info/RECORD
