Metadata-Version: 2.4
Name: everfir_metrics
Version: 0.2.5
Summary: A simple metrics library for everfir
Home-page: https://github.com/everfir/metrics-py
Author: houyibin
Author-email: houyibin@everfir.com
Classifier: Programming Language :: Python :: 3
Classifier: License :: OSI Approved :: MIT License
Classifier: Operating System :: OS Independent
Requires-Python: >=3.6
Requires-Dist: requests>=2.25.0
Requires-Dist: prometheus_client>=0.9.0
Requires-Dist: logger-py>=0.2.3
Requires-Dist: Flask>=2.0.0
Requires-Dist: everfir_logger>=0.0.1
Dynamic: author
Dynamic: author-email
Dynamic: classifier
Dynamic: description-content-type
Dynamic: home-page
Dynamic: requires-dist
Dynamic: requires-python
Dynamic: summary
